{
    "id": 6674498,
    "@id": "http://schema.org/EntryPoint",
    "name": "EntryPoint",
    "title": "Entry Point",
    "description": "An entry point, within some Web-based protocol.",
    "hidden": false,
    "sealed": false,
    "inherits": "Intangible",
    "version":"1.1",
    "fields": [
        {
            "name": "id",
            "title": "ID",
            "description": "The identifier of the item.",
            "type": "Integer",
            "nullable": false,
            "primary": true
        },
        {
            "@id": "http://schema.org/urlTemplate",
            "name": "urlTemplate",
            "title": "Url Template",
            "description": "An url template (RFC6570) that will be used to construct the target of the execution of the action.",
            "type": "Text"
        },
        {
            "@id": "http://schema.org/actionApplication",
            "name": "actionApplication",
            "title": "Action Application",
            "description": "An application that can complete the request.",
            "type": "Text"
        },
        {
            "@id": "http://schema.org/application",
            "name": "application",
            "title": "Application",
            "description": "An application that can complete the request.",
            "type": "Text"
        },
        {
            "@id": "http://schema.org/httpMethod",
            "name": "httpMethod",
            "title": "Http Method",
            "description": "An HTTP method that specifies the appropriate HTTP method for a request to an HTTP EntryPoint. Values are capitalized strings as used in HTTP.",
            "type": "Text"
        },
        {
            "@id": "http://schema.org/encodingType",
            "name": "encodingType",
            "title": "Encoding Type",
            "description": "The supported encoding type(s) for an EntryPoint request.",
            "type": "Text"
        },
        {
            "@id": "http://schema.org/contentType",
            "name": "contentType",
            "title": "Content Type",
            "description": "The supported content type(s) for an EntryPoint response.",
            "type": "Text"
        }
    ],
    "privileges": [
        {
            "mask": 15,
            "type": "global",
            "account": "Administrators"
        },
        {
            "mask": 15,
            "type": "global"
        }
    ]
}